README.md
setup.cfg
setup.py
src/ispyb/__init__.py
src/ispyb/models/__init__.py
src/ispyb/models/_auto_db_schema.py
src/ispyb/models/base.py
src/ispyb_models_daiquiri.egg-info/PKG-INFO
src/ispyb_models_daiquiri.egg-info/SOURCES.txt
src/ispyb_models_daiquiri.egg-info/dependency_links.txt
src/ispyb_models_daiquiri.egg-info/requires.txt
src/ispyb_models_daiquiri.egg-info/top_level.txt
tests/test_models.py