Metadata-Version: 2.1
Name: ispyb-models-daiquiri
Version: 2.0.3
Summary: daiquiri flavour SQLAlchemy ORM models for the ISPyB database
Home-page: https://gitlab.esrf.fr/ui/ispyb-models-daiquiri
Author: ESRF
Author-email: daiquiri-feedback@esrf.fr
License: Apache License, Version 2.0
Keywords: ISPyB,database,SQLAlchemy
Classifier: Development Status :: 5 - Production/Stable
Classifier: License :: OSI Approved :: Apache Software License
Classifier: Programming Language :: Python :: 3
Classifier: Programming Language :: Python :: 3.7
Classifier: Programming Language :: Python :: 3.8
Classifier: Programming Language :: Python :: 3.9
Classifier: Programming Language :: Python :: 3.10
Classifier: Operating System :: OS Independent
Classifier: Topic :: Software Development :: Libraries :: Python Modules
Requires-Python: >=3.7
